esp32_arduino/__init__.py
esp32_arduino/core.py
esp32_arduino/device_manager.py
esp32_arduino/esp32_comm.py
esp32_arduino/solution.py
esp32_arduino/examples/__init__.py
esp32_arduino/examples/dht11_test.py
esp32_arduino/examples/test.py
esp32_arduino/firmware/README.md
esp32_arduino/firmware/firmware.bin
esp32_arduino_python-2.3.0.dist-info/licenses/LICENSE
esp32_arduino_python-2.3.0.dist-info/METADATA
esp32_arduino_python-2.3.0.dist-info/WHEEL
esp32_arduino_python-2.3.0.dist-info/entry_points.txt
esp32_arduino_python-2.3.0.dist-info/top_level.txt
esp32_arduino_python-2.3.0.dist-info/RECORD
