Metadata-Version: 2.4
Name: esp32-arduino-python
Version: 2.3.0
Summary: ESP32 Arduino风格Python控制库 v2.3 - 修复传感器数据读取，完整支持DHT11温湿度传感器
Home-page: https://github.com/dianx12/esp32-arduino-python
Author: Haitao Wang
Author-email: 王海涛 <haitaowang926@gmail.com>
License: MIT
Project-URL: Homepage, https://gitee.com/haitaowang926/esp32-arduino-python
Project-URL: Repository, https://gitee.com/haitaowang926/esp32-arduino-python
Project-URL: Issues, https://gitee.com/haitaowang926/esp32-arduino-python/issues
Classifier: Development Status :: 4 - Beta
Classifier: Intended Audience :: Developers
Classifier: License :: OSI Approved :: MIT License
Classifier: Operating System :: POSIX :: Linux
Classifier: Programming Language :: Python :: 3
Classifier: Programming Language :: Python :: 3.7
Classifier: Programming Language :: Python :: 3.8
Classifier: Programming Language :: Python :: 3.9
Classifier: Programming Language :: Python :: 3.10
Classifier: Topic :: Software Development :: Libraries :: Python Modules
Classifier: Topic :: System :: Hardware
Classifier: Topic :: Scientific/Engineering
Requires-Python: >=3.8
License-File: LICENSE
Requires-Dist: pyserial>=3.5
Dynamic: author
Dynamic: home-page
Dynamic: license-file
Dynamic: requires-python
